tap_bitso/__init__.py
tap_bitso/auth.py
tap_bitso/client.py
tap_bitso/streams.py
tap_bitso/tap.py
tap_bitso-0.7.0.dist-info/METADATA
tap_bitso-0.7.0.dist-info/WHEEL
tap_bitso-0.7.0.dist-info/entry_points.txt
tap_bitso-0.7.0.dist-info/licenses/LICENSE
tap_bitso-0.7.0.dist-info/RECORD
