Metadata-Version: 2.4
Name: tap-bitso
Version: 0.7.0
Summary: `tap-bitso` is a Singer tap for Bitso, built with the Meltano SDK for Singer Taps.
Project-URL: Documentation, https://github.com/reservoir-data/tap-bitso#readme
Project-URL: Homepage, https://github.com/reservoir-data/tap-bitso
Project-URL: Repository, https://github.com/reservoir-data/tap-bitso
Author-email: Edgar Ramírez-Mondragón <edgarrm358@gmail.com>
Maintainer-email: Edgar Ramírez-Mondragón <edgarrm358@gmail.com>
License:                                  Apache License
License-File: LICENSE
Keywords: Bitso,ELT,meltano-sdk,singer.io
Classifier: Programming Language :: Python :: 3 :: Only
Classifier: Programming Language :: Python :: 3.12
Classifier: Programming Language :: Python :: 3.13
Classifier: Programming Language :: Python :: 3.14
Requires-Python: >=3.12
Requires-Dist: requests~=2.32.3
Requires-Dist: singer-sdk~=0.53.2
Requires-Dist: stamina~=25.2.0
